{"nodes": [{"id": "waveK_implC_evidence_report", "label": "Wave K Implementer C Evidence", "file_type": "document", "source_file": "reports/plan250/waveK-implC-evidence.md", "source_location": null, "source_url": null, "captured_at": null, "author": null, "contributor": null}, {"id": "cli_contracts_spec", "label": "CLI Contracts Spec", "file_type": "document", "source_file": "reports/plan250/waveK-implC-evidence.md", "source_location": null, "source_url": null, "captured_at": null, "author": null, "contributor": null}, {"id": "eco_package_guide_doc", "label": "Eco Package Guide", "file_type": "document", "source_file": "reports/plan250/waveK-implC-evidence.md", "source_location": null, "source_url": null, "captured_at": null, "author": null, "contributor": null}], "edges": [{"source": "waveK_implC_evidence_report", "target": "cli_contracts_spec", "relation": "references", "confidence": "EXTRACTED", "confidence_score": 1.0, "source_file": "reports/plan250/waveK-implC-evidence.md", "source_location": null, "weight": 1.0}, {"source": "waveK_implC_evidence_report", "target": "eco_package_guide_doc", "relation": "references", "confidence": "EXTRACTED", "confidence_score": 1.0, "source_file": "reports/plan250/waveK-implC-evidence.md", "source_location": null, "weight": 1.0}], "hyperedges": []}