{"nodes": [{"id": "waved_web_ui_smoke_dom", "label": "WaveD Web UI Smoke DOM", "file_type": "document", "source_file": "reports/plan250/waveD-v0_3_gate/artifacts/test-all/web-ui-smoke.dom.html", "source_location": null, "source_url": null, "captured_at": null, "author": null, "contributor": null}, {"id": "concept_tetra_ui_v1_bundle", "label": "Tetra UI v1 Bundle Validation", "file_type": "rationale", "source_file": "reports/plan250/waveD-v0_3_gate/artifacts/test-all/web-ui-smoke.dom.html", "source_location": null, "source_url": null, "captured_at": null, "author": null, "contributor": null}], "edges": [{"source": "waved_web_ui_smoke_dom", "target": "concept_tetra_ui_v1_bundle", "relation": "references", "confidence": "EXTRACTED", "confidence_score": 1.0, "source_file": "reports/plan250/waveD-v0_3_gate/artifacts/test-all/web-ui-smoke.dom.html", "source_location": null, "weight": 1.0}, {"source": "waved_web_ui_smoke_dom", "target": "concept_web_ui_smoke_check", "relation": "references", "confidence": "INFERRED", "confidence_score": 0.85, "source_file": "reports/plan250/waveD-v0_3_gate/artifacts/test-all/web-ui-smoke.dom.html", "source_location": null, "weight": 0.85}, {"source": "concept_web_ui_smoke_check", "target": "concept_tetra_ui_v1_bundle", "relation": "shares_data_with", "confidence": "INFERRED", "confidence_score": 0.67, "source_file": "reports/plan250/waveD-v0_3_gate/artifacts/test-all/web-ui-smoke.dom.html", "source_location": null, "weight": 0.67}], "hyperedges": []}